npu/script_entry.py
npu/utils.py
neuron_process_utils-2025.9.9.dist-info/METADATA
neuron_process_utils-2025.9.9.dist-info/WHEEL
neuron_process_utils-2025.9.9.dist-info/entry_points.txt
neuron_process_utils-2025.9.9.dist-info/top_level.txt
neuron_process_utils-2025.9.9.dist-info/RECORD
