Metadata-Version: 2.4
Name: neuron-process-utils
Version: 2025.9.9
Summary: neuron process utils
Author-email: jiang yan <1900812927@qq.com>
Project-URL: homepage, https://gitee.com/Eason596/nnunetv2_extend
Project-URL: repository, https://gitee.com/Eason596/nnunetv2_extend
Keywords: neuron process
Requires-Python: >=3.10
Requires-Dist: swcgeom>=0.20.0
Provides-Extra: dev
Requires-Dist: black; extra == "dev"
Requires-Dist: ruff; extra == "dev"
Requires-Dist: pre-commit; extra == "dev"
